phrase_detective/__init__.py
phrase_detective/constants.py
phrase_detective/de/noun_phrases.py
phrase_detective/en/noun_phrases.py
phrase_detective/es/noun_phrases.py
phrase_detective/lib.py
phrase_detective/noun_phrases.py
phrase_detective/regx/__init__.py
phrase_detective/regx/de.py
phrase_detective/regx/en.py
phrase_detective/regx/es.py
phrase_detective/verb_knowledge.py
phrase_detective-0.1.35.dist-info/METADATA
phrase_detective-0.1.35.dist-info/WHEEL
phrase_detective-0.1.35.dist-info/RECORD
