Metadata-Version: 2.1
Name: phrase-detective
Version: 0.1.35
Summary: Phrase recognizer component for spacy pipeline
Home-page: https://github.com/qishe-nlp/phrase-detective
Keywords: phrase detection,NLP,spacy
Author: Phoenix Grey
Author-email: phoenix.grey0108@gmail.com
Requires-Python: >=3.12,<4.0
Classifier: Programming Language :: Python :: 3
Classifier: Programming Language :: Python :: 3.12
Classifier: Programming Language :: Python :: 3.13
Requires-Dist: spacy (==3.7.5)
Project-URL: Documentation, https://qishe-nlp.github.io/phrase-detective/
Project-URL: Repository, https://github.com/qishe-nlp/phrase-detective
